qctrlqiskit/__init__.py
qctrlqiskit/quantum_circuit.py
qctrl_qiskit-0.0.4.dist-info/LICENSE
qctrl_qiskit-0.0.4.dist-info/WHEEL
qctrl_qiskit-0.0.4.dist-info/METADATA
qctrl_qiskit-0.0.4.dist-info/RECORD
